Topsis/__init__.py
Topsis/__main__.py
Topsis_Ayesha_102197019-1.0.0.dist-info/LICENSE
Topsis_Ayesha_102197019-1.0.0.dist-info/METADATA
Topsis_Ayesha_102197019-1.0.0.dist-info/WHEEL
Topsis_Ayesha_102197019-1.0.0.dist-info/entry_points.txt
Topsis_Ayesha_102197019-1.0.0.dist-info/top_level.txt
Topsis_Ayesha_102197019-1.0.0.dist-info/RECORD
