Metadata-Version: 2.1
Name: Topsis-Ayesha-102197019
Version: 1.0.0
Summary: Topsis rank calculator
Home-page: 
Author: Ayesha Sood
Author-email: asood_be20@thapar.edu
License: MIT
Classifier: License :: OSI Approved :: MIT License
Classifier: Programming Language :: Python :: 3.6
Classifier: Programming Language :: Python :: 3.7
Classifier: Programming Language :: Python :: 3.8
License-File: LICENSE
Requires-Dist: numpy
Requires-Dist: pandas
